bitcoin_requests/__init__.py
bitcoin_requests/bitcoin.py
bitcoin_requests-2.0.0.dist-info/LICENSE
bitcoin_requests-2.0.0.dist-info/METADATA
bitcoin_requests-2.0.0.dist-info/WHEEL
bitcoin_requests-2.0.0.dist-info/top_level.txt
bitcoin_requests-2.0.0.dist-info/RECORD
