Metadata-Version: 2.1
Name: bitcoin-requests
Version: 2.0.0
Summary: Simplest Bitcoin Core RPC interface.
Home-page: https://github.com/fiatjaf/bitcoin-requests
Author: fiatjaf
Author-email: fiatjaf@gmail.com
License: MIT
Platform: UNKNOWN
Classifier: License :: OSI Approved :: MIT License
Classifier: Programming Language :: Python :: 3
Classifier: Programming Language :: Python :: 3.7
Requires-Dist: requests
